fds/__init__.py
fds/client.py
fds/config.py
fds/constants.py
fds/models/__init__.py
fds/models/_model.py
fds/models/_use_case.py
fds/models/actions.py
fds/models/determination/__init__.py
fds/models/determination/configuration.py
fds/models/determination/requests.py
fds/models/determination/result.py
fds/models/determination/use_case.py
fds/models/ground_station.py
fds/models/maneuvers/__init__.py
fds/models/maneuvers/result.py
fds/models/maneuvers/strategy.py
fds/models/maneuvers/use_case.py
fds/models/ng/__init__.py
fds/models/orbit_extrapolation/__init__.py
fds/models/orbit_extrapolation/ephemeris.py
fds/models/orbit_extrapolation/events.py
fds/models/orbit_extrapolation/requests.py
fds/models/orbit_extrapolation/result.py
fds/models/orbit_extrapolation/use_case.py
fds/models/orbital_state.py
fds/models/orbits.py
fds/models/quaternion.py
fds/models/roadmaps.py
fds/models/spacecraft.py
fds/models/station_keeping/__init__.py
fds/models/station_keeping/requests.py
fds/models/station_keeping/result.py
fds/models/station_keeping/strategy.py
fds/models/station_keeping/tolerance.py
fds/models/station_keeping/use_case.py
fds/models/strategy.py
fds/models/telemetry.py
fds/models/tle_extrapolation/__init__.py
fds/models/tle_extrapolation/result.py
fds/models/tle_extrapolation/use_case.py
fds/models/two_line_element.py
fds/utils/__init__.py
fds/utils/dates.py
fds/utils/dict.py
fds/utils/enum.py
fds/utils/frames.py
fds/utils/geometry.py
fds/utils/log.py
fds/utils/math.py
fds/utils/nmea.py
fds/utils/orbital_mechanics.py
fds/utils/plotting.py
spacetower_fds_sdk-1.2.2.dist-info/LICENCE.txt
spacetower_fds_sdk-1.2.2.dist-info/METADATA
spacetower_fds_sdk-1.2.2.dist-info/WHEEL
spacetower_fds_sdk-1.2.2.dist-info/RECORD
